LICENSE
MANIFEST.in
README.rst
setup.py
django_http_451.egg-info/PKG-INFO
django_http_451.egg-info/SOURCES.txt
django_http_451.egg-info/dependency_links.txt
django_http_451.egg-info/not-zip-safe
django_http_451.egg-info/requires.txt
django_http_451.egg-info/top_level.txt
http451/__init__.py
http451/admin.py
http451/apps.py
http451/middleware.py
http451/models.py
http451/settings.py
http451/tests.py
http451/views.py
http451/geoip/GeoIP.dat
http451/geoip/GeoLite2-Country.mmdb
http451/templates/blockedResource.html